pythondata_cpu_rocket/__init__.py
pythondata_cpu_rocket/verilog/.gitignore
pythondata_cpu_rocket/verilog/README.md
pythondata_cpu_rocket/verilog/_upstream.rev
pythondata_cpu_rocket/verilog/update.sh
pythondata_cpu_rocket/verilog/generated-src/TestHarness.anno.json
pythondata_cpu_rocket/verilog/generated-src/freechips.rocketchip.system.LitexConfig.0x0.0.regmap.json
pythondata_cpu_rocket/verilog/generated-src/freechips.rocketchip.system.LitexConfig.0x0.1.regmap.json
pythondata_cpu_rocket/verilog/generated-src/freechips.rocketchip.system.LitexConfig.0x2000000.0.regmap.json
pythondata_cpu_rocket/verilog/generated-src/freechips.rocketchip.system.LitexConfig.0x40.0.regmap.json
pythondata_cpu_rocket/verilog/generated-src/freechips.rocketchip.system.LitexConfig.0xc000000.0.regmap.json
pythondata_cpu_rocket/verilog/generated-src/freechips.rocketchip.system.LitexConfig.anno.json
pythondata_cpu_rocket/verilog/generated-src/freechips.rocketchip.system.LitexConfig.behav_srams.v
pythondata_cpu_rocket/verilog/generated-src/freechips.rocketchip.system.LitexConfig.conf
pythondata_cpu_rocket/verilog/generated-src/freechips.rocketchip.system.LitexConfig.d
pythondata_cpu_rocket/verilog/generated-src/freechips.rocketchip.system.LitexConfig.dts
pythondata_cpu_rocket/verilog/generated-src/freechips.rocketchip.system.LitexConfig.fir
pythondata_cpu_rocket/verilog/generated-src/freechips.rocketchip.system.LitexConfig.graphml
pythondata_cpu_rocket/verilog/generated-src/freechips.rocketchip.system.LitexConfig.json
pythondata_cpu_rocket/verilog/generated-src/freechips.rocketchip.system.LitexConfig.memmap.json
pythondata_cpu_rocket/verilog/generated-src/freechips.rocketchip.system.LitexConfig.plusArgs
pythondata_cpu_rocket/verilog/generated-src/freechips.rocketchip.system.LitexConfig.rom.conf
pythondata_cpu_rocket/verilog/generated-src/freechips.rocketchip.system.LitexConfig.v
pythondata_cpu_rocket/verilog/generated-src/freechips.rocketchip.system.LitexFull4DConfig.0x0.0.regmap.json
pythondata_cpu_rocket-0.0.post7146.dist-info/LICENSE
pythondata_cpu_rocket-0.0.post7146.dist-info/METADATA
pythondata_cpu_rocket-0.0.post7146.dist-info/WHEEL
pythondata_cpu_rocket-0.0.post7146.dist-info/top_level.txt
pythondata_cpu_rocket-0.0.post7146.dist-info/RECORD
