Metadata-Version: 2.1
Name: pythondata-cpu-rocket
Version: 0.0.post7146
Summary: Python module containing verilog files for Rocket cpu.
Home-page: https://github.com/litex-hub/pythondata-cpu-rocket
Author: LiteX Authors
Author-email: litex@googlegroups.com
Project-URL: Bug Tracker, https://github.com/litex-hub/pythondata-cpu-rocket/issues
Project-URL: Source Code, https://github.com/litex-hub/pythondata-cpu-rocket
Classifier: Programming Language :: Python :: 3
Classifier: License :: OSI Approved :: Apache Software License
Classifier: Operating System :: OS Independent
Requires-Python: >=3.5
License-File: LICENSE
